nibe/__init__.py
nibe/coil.py
nibe/coil_groups.py
nibe/event_server.py
nibe/exceptions.py
nibe/heatpump.py
nibe/parsers.py
nibe/py.typed
nibe/connection/__init__.py
nibe/connection/encoders.py
nibe/connection/mixins.py
nibe/connection/modbus.py
nibe/connection/nibegw.py
nibe/console_scripts/__init__.py
nibe/console_scripts/cli.py
nibe/console_scripts/convert_csv.py
nibe/data/__init__.py
nibe/data/extensions.json
nibe/data/f1145_f1245.json
nibe/data/f1155_f1255.json
nibe/data/f1345.json
nibe/data/f1355.json
nibe/data/f370_f470.json
nibe/data/f730.json
nibe/data/f750.json
nibe/data/s1155_s1255.json
nibe/data/s1156_s1256.json
nibe/data/s2125.json
nibe/data/s320_s325.json
nibe/data/s330_s332.json
nibe/data/s735.json
nibe/data/smo20.json
nibe/data/smo40.json
nibe/data/smos40.json
nibe/data/vvm225_vvm320_vvm325.json
nibe/data/vvm310_vvm500.json
nibe/data/vvms325.json
nibe-2.20.0.dist-info/licenses/LICENSE
nibe-2.20.0.dist-info/METADATA
nibe-2.20.0.dist-info/WHEEL
nibe-2.20.0.dist-info/entry_points.txt
nibe-2.20.0.dist-info/top_level.txt
nibe-2.20.0.dist-info/zip-safe
nibe-2.20.0.dist-info/RECORD
