Metadata-Version: 2.4
Name: nibe
Version: 2.20.0
Summary: Nibe heatpump communication library
Home-page: https://github.com/yozik04/nibe
Author: Jevgeni Kiski
Author-email: yozik04@gmail.com
License: LGPL 3
Project-URL: Bug Tracker, https://github.com/yozik04/nibe/issues
Keywords: nibe modbus library nibegw
Classifier: Development Status :: 5 - Production/Stable
Classifier: Intended Audience :: Developers
Classifier: License :: OSI Approved :: GNU Lesser General Public License v3 (LGPLv3)
Classifier: Operating System :: OS Independent
Classifier: Programming Language :: Python
Classifier: Programming Language :: Python :: 3 :: Only
Classifier: Programming Language :: Python :: 3.9
Classifier: Programming Language :: Python :: 3.10
Classifier: Programming Language :: Python :: 3.11
Classifier: Programming Language :: Python :: 3.12
Classifier: Programming Language :: Python :: 3.13
Classifier: Programming Language :: Python :: 3.14
Requires-Python: >=3.9
License-File: LICENSE
Requires-Dist: construct<3.0.0,>=2.10.0
Requires-Dist: async_modbus>=0.2.2
Requires-Dist: async_timeout>=4.0.0
Requires-Dist: tenacity>=8.0.0
Requires-Dist: exceptiongroup>=1.0.0
Provides-Extra: convert
Requires-Dist: pandas>=1.0.5; extra == "convert"
Requires-Dist: python-slugify>=4.0.0; extra == "convert"
Provides-Extra: cli
Requires-Dist: asyncclick>=8.1.3.4; extra == "cli"
Dynamic: license-file
